[{
    "customizable": true,
    "enterprise": false,
    "feeds": [{
        "id": "feed/http://brandonsanderson.com/feed/",
        "feedId": "feed/http://brandonsanderson.com/feed/",
        "title": "Writing Excuses Workshop and Retreat 2019 + Weekly Update",
        "updated": 1551993625583,
        "velocity": 0.2,
        "subscribers": 3142,
        "website": "https://brandonsanderson.com",
        "topics": ["books", "authors", "writing"],
        "partial": false,
        "coverUrl": "https://storage.googleapis.com/site-assets/4FJtBKITg6WOu2mWu9n35XSizzk-s8Ybr9IRGBdVE7s_cover-166fcb440b4",
        "iconUrl": "https://storage.googleapis.com/site-assets/4FJtBKITg6WOu2mWu9n35XSizzk-s8Ybr9IRGBdVE7s_icon-15b9282e528",
        "visualUrl": "https://storage.googleapis.com/site-assets/4FJtBKITg6WOu2mWu9n35XSizzk-s8Ybr9IRGBdVE7s_visual-15b9282e528",
        "contentType": "article",
        "language": "en",
        "description": "Brandon Sanderson's Official Website",
        "coverColor": "C0DEED"
    }, {
        "id": "feed/http://mark---lawrence.blogspot.com/feeds/posts/default",
        "feedId": "feed/http://mark---lawrence.blogspot.com/feeds/posts/default",
        "title": "Mark Lawrence",
        "updated": 1551178998994,
        "velocity": 1.1,
        "subscribers": 320,
        "website": "http://mark---lawrence.blogspot.com/",
        "topics": ["books", "authors", "writing", "fantasy football"],
        "partial": false,
        "contentType": "article",
        "language": "en",
        "description": "I'm the author of The Broken Empire, The Red Queen's War, & Book of the Ancestor trilogies - spare ideas land here.         \n ______________ Twitter @mark__lawrence (2 underscores!)"
    }, {
        "id": "feed/https://scribbler.john-mendez.com/feed/",
        "feedId": "feed/https://scribbler.john-mendez.com/feed/",
        "title": "John Mendez- Book Reviews and More",
        "updated": 1551902304226,
        "velocity": 3.2,
        "subscribers": 1,
        "website": "https://scribbler.john-mendez.com",
        "language": "en",
        "description": "scribblermendez"
    }, {
        "id": "feed/https://thequilltolive.com/feed/",
        "feedId": "feed/https://thequilltolive.com/feed/",
        "title": "The Quill to Live",
        "updated": 1551809213246,
        "velocity": 2.0,
        "subscribers": 52,
        "website": "https://thequilltolive.com",
        "topics": ["books", "fantasy football", "san francisco", "scifi", "reading", "storytelling"],
        "partial": false,
        "iconUrl": "https://storage.googleapis.com/site-assets/qlvbVtxtPRR12wd9n0MdVqtMOCxWXxxNlTRzzAcylkc_sicon-1624d29a96e",
        "visualUrl": "https://storage.googleapis.com/site-assets/qlvbVtxtPRR12wd9n0MdVqtMOCxWXxxNlTRzzAcylkc_svisual-1624d29a96e",
        "contentType": "longform",
        "language": "en",
        "description": "Books Worth Staying In Bed For"
    }, {
        "id": "feed/http://www.brianmcclellan.com/blog?format=RSS",
        "feedId": "feed/http://www.brianmcclellan.com/blog?format=RSS",
        "title": "Brian McClellan",
        "updated": 1551721932590,
        "velocity": 0.7,
        "subscribers": 82,
        "website": "http://www.brianmcclellan.com/",
        "topics": ["books", "authors", "writing"],
        "partial": false,
        "coverUrl": "https://storage.googleapis.com/site-assets/yBSm-M-FwpQYx8072k295JuVcD-9eQ2WZN1LevzBl6Y_cover-162afb09357",
        "iconUrl": "https://storage.googleapis.com/site-assets/yBSm-M-FwpQYx8072k295JuVcD-9eQ2WZN1LevzBl6Y_icon-16144a8d7b6",
        "visualUrl": "https://storage.googleapis.com/site-assets/yBSm-M-FwpQYx8072k295JuVcD-9eQ2WZN1LevzBl6Y_visual-16144a8d7b6",
        "contentType": "article",
        "language": "en",
        "description": "Official website of Brian McClellan, author of The Power Mage Trilogy, Gods \r\nof Blood and Powder, and various other works.",
        "coverColor": "C0DEED"
    }],
    "label": "Books",
    "numFeeds": 5,
    "id": "user/e8ca5f09-ffa1-43d8-9f28-867ed8ad876a/category/Books"
}, {
    "customizable": true,
    "enterprise": false,
    "feeds": [{
        "id": "feed/http://hacks.mozilla.org/feed/",
        "feedId": "feed/http://hacks.mozilla.org/feed/",
        "title": "Mozilla Hacks – the Web developer blog",
        "updated": 1551973506209,
        "velocity": 1.6,
        "subscribers": 22477,
        "website": "https://hacks.mozilla.org",
        "topics": ["javascript", "browsers", "tech", "frontend standards"],
        "partial": false,
        "iconUrl": "https://storage.googleapis.com/site-assets/dPA20yDKj7MHgyIRjOX2OOk1cb-5A4xCS8qqqclHcbY_icon-15b926f4318",
        "visualUrl": "https://storage.googleapis.com/site-assets/dPA20yDKj7MHgyIRjOX2OOk1cb-5A4xCS8qqqclHcbY_visual-15b926f4318",
        "contentType": "longform",
        "language": "en",
        "description": "Mozilla Hacks is written for web developers, designers and everyone who builds for the Web. Hacks is produced by Mozilla's Developer Relations team and features hundreds of posts from Mozilla ...",
        "coverColor": "454545"
    }, {
        "id": "feed/http://blog.chromium.org/feeds/posts/default",
        "feedId": "feed/http://blog.chromium.org/feeds/posts/default",
        "title": "Chromium Blog",
        "updated": 1549659830215,
        "velocity": 0.2,
        "subscribers": 25382,
        "website": "http://blog.chromium.org/",
        "topics": ["google", "tech", "programming", "web design", "browsers"],
        "partial": false,
        "iconUrl": "https://storage.googleapis.com/site-assets/Q_v56NShbXV_Mb5JnBWdLOCzhh7xZOJ3jEFKwDr_kxY_sicon-1603f722289",
        "visualUrl": "https://storage.googleapis.com/site-assets/Q_v56NShbXV_Mb5JnBWdLOCzhh7xZOJ3jEFKwDr_kxY_svisual-1603f722289",
        "contentType": "longform",
        "language": "en",
        "description": "News and developments from the open source browser project"
    }, {
        "id": "feed/https://blog.nightly.mozilla.org/feed/",
        "feedId": "feed/https://blog.nightly.mozilla.org/feed/",
        "title": "Firefox Nightly News",
        "updated": 1551799629796,
        "velocity": 0.5,
        "subscribers": 641,
        "website": "https://blog.nightly.mozilla.org",
        "topics": ["tech", "mozilla", "programming", "browsers", "software"],
        "partial": false,
        "coverUrl": "https://storage.googleapis.com/site-assets/US0mgh0DVd3Tvd7BHcc4fvPLQEwcVR0zxqevEgTyX0E_cover-15dd3eee522",
        "iconUrl": "https://storage.googleapis.com/site-assets/US0mgh0DVd3Tvd7BHcc4fvPLQEwcVR0zxqevEgTyX0E_icon-15dd3eee522",
        "visualUrl": "https://storage.googleapis.com/site-assets/US0mgh0DVd3Tvd7BHcc4fvPLQEwcVR0zxqevEgTyX0E_visual-15dd3eee522",
        "contentType": "longform",
        "language": "en",
        "description": "Let's improve quality, build after build!",
        "coverColor": "10445E",
        "twitterScreenName": "FirefoxNightly",
        "twitterFollowers": 20425
    }, {
        "id": "feed/http://www.eff.org/rss/updates.xml",
        "feedId": "feed/http://www.eff.org/rss/updates.xml",
        "title": "Deeplinks",
        "updated": 1552005586877,
        "velocity": 10.4,
        "subscribers": 24582,
        "website": "https://www.eff.org/rss/updates.xml",
        "topics": ["tech", "security", "privacy", "law"],
        "partial": false,
        "coverUrl": "https://storage.googleapis.com/site-assets/oEr_GaRGcRnheuP-PyXeZnJ-BHD-nv7Tk0KoSHxLKyI_cover-1694ed2160a",
        "iconUrl": "https://storage.googleapis.com/site-assets/oEr_GaRGcRnheuP-PyXeZnJ-BHD-nv7Tk0KoSHxLKyI_icon-164dfb6007e",
        "visualUrl": "https://storage.googleapis.com/site-assets/oEr_GaRGcRnheuP-PyXeZnJ-BHD-nv7Tk0KoSHxLKyI_visual-164dfb6007e",
        "contentType": "longform",
        "language": "en",
        "description": "EFF's Deeplinks Blog: Noteworthy news from around the internet",
        "coverColor": "E17701"
    }, {
        "id": "feed/http://blog.mozilla.com/feed/",
        "feedId": "feed/http://blog.mozilla.com/feed/",
        "title": "The Mozilla Blog",
        "updated": 1551352866728,
        "velocity": 2.0,
        "subscribers": 15034,
        "website": "https://blog.mozilla.org",
        "topics": ["tech", "mozilla", "programming", "web design", "software", "browsers"],
        "partial": false,
        "coverUrl": "https://storage.googleapis.com/site-assets/bNvrb5gCfVC25fV_lYFtkqBMJxL_FU742UZmJ2VM_bk_cover-164f6e29fbf",
        "iconUrl": "https://storage.googleapis.com/site-assets/bNvrb5gCfVC25fV_lYFtkqBMJxL_FU742UZmJ2VM_bk_icon-16372b77a2c",
        "visualUrl": "https://storage.googleapis.com/site-assets/bNvrb5gCfVC25fV_lYFtkqBMJxL_FU742UZmJ2VM_bk_visual-16372b77a2c",
        "contentType": "longform",
        "language": "en",
        "description": "Dispatches from the Internet frontier.",
        "coverColor": "131516"
    }, {
        "id": "feed/http://jakearchibald.com/posts.rss",
        "feedId": "feed/http://jakearchibald.com/posts.rss",
        "title": "Jake Archibald's Blog",
        "updated": 1546871135770,
        "velocity": 0.1,
        "subscribers": 5842,
        "website": "http://jakearchibald.com/",
        "topics": ["web design", "programming", "tech", "javascript"],
        "partial": false,
        "contentType": "longform",
        "language": "en",
        "description": "Witterings of a web developer"
    }],
    "label": "Browsers",
    "numFeeds": 6,
    "id": "user/e8ca5f09-ffa1-43d8-9f28-867ed8ad876a/category/Browsers"
}, {
    "customizable": true,
    "enterprise": false,
    "feeds": [{
        "id": "feed/http://www.theverge.com/rss/full.xml",
        "feedId": "feed/http://www.theverge.com/rss/full.xml",
        "title": "The Verge",
        "updated": 1552040435376,
        "velocity": 236.6,
        "subscribers": 1118404,
        "website": "https://www.theverge.com/",
        "topics": ["tech"],
        "partial": false,
        "coverUrl": "https://storage.googleapis.com/site-assets/PSNTZO8gXFUe-cpCZyApw0vEKWPT4b14D6teBEocIAE_cover-160e45fc68d",
        "iconUrl": "https://storage.googleapis.com/site-assets/PSNTZO8gXFUe-cpCZyApw0vEKWPT4b14D6teBEocIAE_icon-15cd6b8692d",
        "visualUrl": "https://storage.googleapis.com/site-assets/PSNTZO8gXFUe-cpCZyApw0vEKWPT4b14D6teBEocIAE_visual-15cd6b8692d",
        "contentType": "longform",
        "language": "en",
        "description": "Covering the intersection of technology, science, art, and culture.",
        "coverColor": "FFFFFF",
        "logo": "http://storage.googleapis.com/test-site-assets/PSNTZO8gXFUe-cpCZyApw0vEKWPT4b14D6teBEocIAE_ologo-14be62cd987",
        "wordmark": "http://storage.googleapis.com/test-site-assets/PSNTZO8gXFUe-cpCZyApw0vEKWPT4b14D6teBEocIAE_owordmark-1503a52ff7f",
        "relatedLayout": "card",
        "relatedTarget": "browser",
        "accentColor": "fa4b2a"
    }],
    "label": "Technology",
    "numFeeds": 1,
    "id": "user/e8ca5f09-ffa1-43d8-9f28-867ed8ad876a/category/Technology"
}, {
    "customizable": false,
    "enterprise": false,
    "feeds": [{
        "id": "feed/http://feeds.feedburner.com/Torrentfreak",
        "feedId": "feed/http://feeds.feedburner.com/Torrentfreak",
        "title": "TorrentFreak",
        "updated": 1552036176985,
        "velocity": 16.0,
        "subscribers": 54634,
        "website": "https://torrentfreak.com",
        "topics": ["tech", "torrents", "news"],
        "partial": false,
        "coverUrl": "http://storage.googleapis.com/site-assets/EZXJpQIki4w-I1Se9c1fhZBH9nDCwb-p40wQMbJRYCQ_cover-154150f8d81",
        "iconUrl": "http://storage.googleapis.com/site-assets/EZXJpQIki4w-I1Se9c1fhZBH9nDCwb-p40wQMbJRYCQ_icon-154150f8d81",
        "visualUrl": "http://storage.googleapis.com/site-assets/EZXJpQIki4w-I1Se9c1fhZBH9nDCwb-p40wQMbJRYCQ_visual-154150f8d81",
        "contentType": "longform",
        "language": "en",
        "description": "Breaking File-sharing, Copyright and Privacy News",
        "coverColor": "636464"
    }, {
        "id": "feed/http://feeds.feedburner.com/TheAtlantic",
        "feedId": "feed/http://feeds.feedburner.com/TheAtlantic",
        "title": "The Atlantic",
        "updated": 1552040397102,
        "velocity": 119.7,
        "subscribers": 181610,
        "website": "https://www.theatlantic.com/",
        "topics": ["news", "politics", "culture", "magazines"],
        "partial": false,
        "coverUrl": "https://storage.googleapis.com/site-assets/PiZyxgIkdjlmli7o0PIIinzT0eRAK6XGvK0WaTRcMRg_cover-15cc7ba7011",
        "iconUrl": "https://storage.googleapis.com/site-assets/PiZyxgIkdjlmli7o0PIIinzT0eRAK6XGvK0WaTRcMRg_icon-15cf2d2e609",
        "visualUrl": "https://storage.googleapis.com/site-assets/PiZyxgIkdjlmli7o0PIIinzT0eRAK6XGvK0WaTRcMRg_visual-15cf2d2e609",
        "contentType": "longform",
        "language": "en",
        "description": "The Atlantic covers breaking news, analysis, opinion around politics, business, culture, international, science, technology, national and food on the official site of the Atlantic Magazine.",
        "coverColor": "000000",
        "logo": "http://storage.googleapis.com/test-site-assets/PiZyxgIkdjlmli7o0PIIinzT0eRAK6XGvK0WaTRcMRg_ologo-14d5491b7e0",
        "relatedLayout": "card",
        "relatedTarget": "browser",
        "accentColor": "#458CD5"
    }, {
        "id": "feed/http://syndication.thedailywtf.com/TheDailyWtf",
        "feedId": "feed/http://syndication.thedailywtf.com/TheDailyWtf",
        "title": "The Daily WTF",
        "updated": 1551958264857,
        "velocity": 5.4,
        "subscribers": 63639,
        "website": "http://thedailywtf.com/",
        "topics": ["programming", "comics", "tech"],
        "partial": false,
        "iconUrl": "http://storage.googleapis.com/site-assets/WPn7zSiuQJvsu0IB4KBgvZCf3wMpC8Uq3PbuzUsCJCg_sicon-1541393c020",
        "visualUrl": "http://storage.googleapis.com/site-assets/WPn7zSiuQJvsu0IB4KBgvZCf3wMpC8Uq3PbuzUsCJCg_svisual-1541393c020",
        "contentType": "article",
        "language": "en",
        "description": "Curious Perversions in Information Technology."
    }],
    "label": "Uncategorized",
    "numFeeds": 3,
    "id": "user/e8ca5f09-ffa1-43d8-9f28-867ed8ad876a/category/global.uncategorized"
}]